README
setup.py
pynvvm/__init__.py
pynvvm/compiler.py
pynvvm/interface.py
pynvvm.egg-info/PKG-INFO
pynvvm.egg-info/SOURCES.txt
pynvvm.egg-info/dependency_links.txt
pynvvm.egg-info/top_level.txt