Metadata-Version: 1.1
Name: pynvvm
Version: 1.0.1
Summary: Python bindings to libNVVM.
Home-page: https://github.com/nvidia-compiler-sdk/pynvvm/
Author: Justin Holewinski
Author-email: jholewinski@nvidia.com
License: MIT
Platform: UNKNOWN
Classifier: Development Status :: 5 - Production/Stable
Classifier: Environment :: Console
Classifier: Intended Audience :: Science/Research
Classifier: Intended Audience :: Developers
Classifier: License :: OSI Approved :: MIT License
Classifier: Operating System :: MacOS :: MacOS X
Classifier: Operating System :: Microsoft :: Windows
Classifier: Operating System :: POSIX
Classifier: Programming Language :: Python
Classifier: Topic :: Software Development :: Compilers
Classifier: Topic :: Software Development :: Libraries
